{
  "id": "monster-tyrannosaurus-rex",
  "slug": "tyrannosaurus-rex",
  "name": {
    "es": "Tiranosaurio Rex",
    "en": "Tyrannosaurus Rex"
  },
  "size": {
    "es": "Enorme",
    "en": "Large"
  },
  "type": {
    "es": "Bestia (dinosaurio)",
    "en": "creature"
  },
  "alignment": {
    "es": "Sin alineamiento",
    "en": "it has the Grappled condition"
  },
  "armorClass": 10,
  "hitPoints": "19 (3dI0 + 3)",
  "speed": {
    "es": "3 m, volar 15 m",
    "en": "10 ft., Fly 50 ft."
  },
  "abilityScores": {
    "str": 10,
    "dex": 10,
    "con": 10,
    "int": 10,
    "wis": 10,
    "cha": 10
  },
  "skills": {
    "es": "Percepción +3",
    "en": "Perception +3"
  },
  "senses": {
    "es": "Vista ciega 3 m; Percepción pasiva 10",
    "en": "Blindsight 10 ft.; Passive Perception 10"
  },
  "languages": {
    "es": "None",
    "en": "None"
  },
  "challengeRating": "0",
  "proficiencyBonus": "+2",
  "traits": [],
  "actions": [],
  "bonusActions": [],
  "reactions": [],
  "legendaryActions": [],
  "description": {
    "es": "Del Manual de Monstruos (libro p.372). Estadísticas extraídas por OCR; verificar con el PDF.",
    "en": "From Monster Manual (book p.372). Stats OCR-extracted; verify vs PDF."
  },
  "source": "mm"
}
