{
  "id": "monster-will-o1wisp",
  "slug": "will-o1wisp",
  "name": {
    "es": "Fuego fatuo",
    "en": "Will-o1Wisp"
  },
  "size": {
    "es": "Diminuto",
    "en": "Large"
  },
  "type": {
    "es": "Muerto viviente",
    "en": "Monstrosity"
  },
  "alignment": {
    "es": "Caótico malvado",
    "en": "Neutral Evil"
  },
  "armorClass": 13,
  "hitPoints": "75 (10d10 + 20)",
  "speed": {
    "es": "15 m",
    "en": "50 ft."
  },
  "abilityScores": {
    "str": 10,
    "dex": 10,
    "con": 10,
    "int": 10,
    "wis": 10,
    "cha": 10
  },
  "skills": {
    "es": "Percepción +5, Sigilo +5",
    "en": "Perception +5, Stealth +5"
  },
  "senses": {
    "es": "Percepción pasiva 15",
    "en": "Passive Perception 15"
  },
  "languages": {
    "es": "Común, C iant",
    "en": "Common, C iant"
  },
  "challengeRating": "3",
  "proficiencyBonus": "+2",
  "traits": [],
  "actions": [],
  "bonusActions": [],
  "reactions": [],
  "legendaryActions": [],
  "description": {
    "es": "Del Manual de Monstruos (libro p.333). Estadísticas extraídas por OCR; verificar con el PDF.",
    "en": "From Monster Manual (book p.333). Stats OCR-extracted; verify vs PDF."
  },
  "source": "mm"
}
